final_project/fpga/rtl/io/led_status.v
`timescale 1ns / 1ps

module led_status #(
    parameter integer CLK_HZ        = 25_200_000,
    parameter integer COMMAND_MS    = 150,
    parameter integer PROTOCOL_MS   = 200,
    parameter integer FATAL_HALF_MS = 100
)(
    input  wire clk,
    input  wire rst_n,

    // Um comando valido foi recebido/executado.
    input  wire accepted_pulse,

    // Erro de protocolo ou comando invalido.
    input  wire protocol_error_pulse,

    // Erro grave. No projeto atual, corresponde ao overflow do MAC.
    input  wire fatal_error,

    // Limpa o erro grave armazenado.
    input  wire clear_pulse,

    // LED onboard da Tang Nano 4K.
    output reg led_pin
);

    /*
     * ============================================================
     * Tempos dos padroes
     * ============================================================
     *
     * Comando aceito:
     *     1 piscada de aproximadamente 150 ms
     *
     * Erro de protocolo:
     *     aceso 200 ms
     *     apagado 200 ms
     *     aceso 200 ms
     *
     * Erro grave:
     *     alterna a cada 100 ms continuamente ate CLEAR
     */

    localparam integer COMMAND_CYCLES =
        (CLK_HZ / 1000) * COMMAND_MS;

    localparam integer PROTOCOL_CYCLES =
        (CLK_HZ / 1000) * PROTOCOL_MS;

    localparam integer FATAL_HALF_CYCLES =
        (CLK_HZ / 1000) * FATAL_HALF_MS;


    /*
     * ============================================================
     * Estados da maquina de estados
     * ============================================================
     */

    localparam [2:0] S_IDLE       = 3'd0;
    localparam [2:0] S_COMMAND    = 3'd1;
    localparam [2:0] S_PROTO_ON_1 = 3'd2;
    localparam [2:0] S_PROTO_OFF  = 3'd3;
    localparam [2:0] S_PROTO_ON_2 = 3'd4;
    localparam [2:0] S_FATAL      = 3'd5;

    reg [2:0]  state;
    reg [31:0] timer;

    /*
     * fatal_latched guarda a informacao de erro grave.
     *
     * Mesmo que fatal_error dure somente um ciclo,
     * o LED continua piscando ate clear_pulse.
     */
    reg fatal_latched;


    /*
     * ============================================================
     * Logica principal
     * ============================================================
     */

    always @(posedge clk or negedge rst_n) begin

        /*
         * RESET
         */
        if (!rst_n) begin
            state         <= S_IDLE;
            timer         <= 32'd0;
            fatal_latched <= 1'b0;
            led_pin       <= 1'b0;
        end

        /*
         * CLEAR possui prioridade para apagar os estados de erro.
         */
        else if (clear_pulse) begin
            state         <= S_IDLE;
            timer         <= 32'd0;
            fatal_latched <= 1'b0;
            led_pin       <= 1'b0;
        end

        else begin

            /*
             * Se ocorrer erro grave, memorize-o.
             */
            if (fatal_error)
                fatal_latched <= 1'b1;


            /*
             * ====================================================
             * PRIORIDADE 1: ERRO GRAVE
             * ====================================================
             *
             * Piscada rapida continua:
             *
             * 100 ms ON
             * 100 ms OFF
             * 100 ms ON
             * ...
             *
             * So para quando chega CLEAR.
             */

            if (fatal_latched || fatal_error) begin

                state <= S_FATAL;

                if (timer >= FATAL_HALF_CYCLES - 1) begin
                    timer   <= 32'd0;
                    led_pin <= ~led_pin;
                end
                else begin
                    timer <= timer + 1'b1;
                end
            end


            /*
             * ====================================================
             * PRIORIDADE 2: ERRO DE PROTOCOLO
             * ====================================================
             */

            else if (protocol_error_pulse) begin
                state   <= S_PROTO_ON_1;
                timer   <= 32'd0;
                led_pin <= 1'b1;
            end


            /*
             * ====================================================
             * Estados normais
             * ====================================================
             */

            else begin

                case (state)

                    /*
                     * ------------------------------------------------
                     * Nenhum evento.
                     * LED apagado.
                     * ------------------------------------------------
                     */
                    S_IDLE: begin
                        timer   <= 32'd0;
                        led_pin <= 1'b0;

                        /*
                         * Um comando aceito inicia uma piscada curta.
                         */
                        if (accepted_pulse) begin
                            state   <= S_COMMAND;
                            timer   <= 32'd0;
                            led_pin <= 1'b1;
                        end
                    end


                    /*
                     * ------------------------------------------------
                     * Uma piscada curta para comando aceito.
                     * ------------------------------------------------
                     */
                    S_COMMAND: begin

                        if (timer >= COMMAND_CYCLES - 1) begin
                            state   <= S_IDLE;
                            timer   <= 32'd0;
                            led_pin <= 1'b0;
                        end
                        else begin
                            timer <= timer + 1'b1;
                        end
                    end


                    /*
                     * ------------------------------------------------
                     * Primeira piscada do erro de protocolo.
                     * ------------------------------------------------
                     */
                    S_PROTO_ON_1: begin

                        if (timer >= PROTOCOL_CYCLES - 1) begin
                            state   <= S_PROTO_OFF;
                            timer   <= 32'd0;
                            led_pin <= 1'b0;
                        end
                        else begin
                            timer <= timer + 1'b1;
                        end
                    end


                    /*
                     * ------------------------------------------------
                     * Intervalo apagado entre as duas piscadas.
                     * ------------------------------------------------
                     */
                    S_PROTO_OFF: begin

                        if (timer >= PROTOCOL_CYCLES - 1) begin
                            state   <= S_PROTO_ON_2;
                            timer   <= 32'd0;
                            led_pin <= 1'b1;
                        end
                        else begin
                            timer <= timer + 1'b1;
                        end
                    end


                    /*
                     * ------------------------------------------------
                     * Segunda piscada do erro de protocolo.
                     * ------------------------------------------------
                     */
                    S_PROTO_ON_2: begin

                        if (timer >= PROTOCOL_CYCLES - 1) begin
                            state   <= S_IDLE;
                            timer   <= 32'd0;
                            led_pin <= 1'b0;
                        end
                        else begin
                            timer <= timer + 1'b1;
                        end
                    end


                    /*
                     * ------------------------------------------------
                     * Normalmente não chegamos aqui pelo case,
                     * porque o erro grave é tratado antes.
                     *
                     * Este estado existe apenas para deixar a FSM
                     * completa e segura.
                     * ------------------------------------------------
                     */
                    S_FATAL: begin
                        state   <= S_IDLE;
                        timer   <= 32'd0;
                        led_pin <= 1'b0;
                    end


                    /*
                     * ------------------------------------------------
                     * Protecao contra estado desconhecido.
                     * ------------------------------------------------
                     */
                    default: begin
                        state   <= S_IDLE;
                        timer   <= 32'd0;
                        led_pin <= 1'b0;
                    end

                endcase
            end
        end
    end

endmodule

final_project/fpga/sim/tb_led_status.v
`timescale 1ns/1ps
module tb_led_status;
  reg clk = 1'b0;
  reg rst_n = 1'b0;
  reg accepted_pulse = 1'b0;
  reg protocol_error_pulse = 1'b0;
  reg fatal_error = 1'b0;
  reg clear_pulse = 1'b0;
  wire led_pin;

  integer failures = 0;
  integer rise_count = 0;
  integer toggle_count = 0;
  reg previous_led = 1'b0;
  integer baseline;

  always #5 clk = ~clk;

  always @(posedge clk) begin
    if (rst_n) begin
      if (led_pin && !previous_led)
        rise_count = rise_count + 1;
      if (led_pin != previous_led)
        toggle_count = toggle_count + 1;
        previous_led <= led_pin;
    end
  end

  led_status #(
    .CLK_HZ(1000),
    .COMMAND_MS(4),
    .PROTOCOL_MS(2),
    .FATAL_HALF_MS(2)
  ) dut (
    .clk(clk),
    .rst_n(rst_n),
    .accepted_pulse(accepted_pulse),
    .protocol_error_pulse(protocol_error_pulse),
    .fatal_error(fatal_error),
    .clear_pulse(clear_pulse),
    .led_pin(led_pin)
  );

  initial begin
    $dumpfile("build/tb_led_status.vcd");
    $dumpvars(0, tb_led_status);

    repeat (3) @(negedge clk);
    rst_n = 1'b1;
    repeat (2) @(negedge clk);

    // Comando aceito: uma piscada e retorno ao apagado.
    baseline = rise_count;
    accepted_pulse = 1'b1;
    @(negedge clk); accepted_pulse = 1'b0;
    repeat (8) @(negedge clk);
    if (rise_count - baseline < 1 || led_pin !== 1'b0)
      failures = failures + 1;

    // Erro de protocolo: duas piscadas e retorno ao apagado.
    baseline = rise_count;
    protocol_error_pulse = 1'b1;
    @(negedge clk); protocol_error_pulse = 1'b0;
    repeat (12) @(negedge clk);
    if (rise_count - baseline < 2 || led_pin !== 1'b0)
      failures = failures + 1;

    // Erro grave: piscada continua ate CLEAR.
    baseline = toggle_count;
    fatal_error = 1'b1;
    @(negedge clk); fatal_error = 1'b0;
    repeat (12) @(negedge clk);
    if (toggle_count - baseline < 4)
      failures = failures + 1;

    clear_pulse = 1'b1;
    @(negedge clk); clear_pulse = 1'b0;
    repeat (2) @(negedge clk);
    if (led_pin !== 1'b0)
      failures = failures + 1;

    if (failures == 0)
      $display("PASS tb_led_status");
    else
      $fatal(1, "FALHA tb_led_status: %0d erros", failures);
    $finish;
  end
endmodule

final_project/fpga/sim/build/tb_led_status.vcd
$date
	Mon Sep 28 19:07:40 2026
$end
$version
	Icarus Verilog
$end
$timescale
	1ps
$end
$scope module tb_led_status $end
$var wire 1 ! led_pin $end
$var reg 1 " accepted_pulse $end
$var reg 1 # clear_pulse $end
$var reg 1 $ clk $end
$var reg 1 % fatal_error $end
$var reg 1 & previous_led $end
$var reg 1 ' protocol_error_pulse $end
$var reg 1 ( rst_n $end
$var integer 32 ) baseline [31:0] $end
$var integer 32 * failures [31:0] $end
$var integer 32 + rise_count [31:0] $end
$var integer 32 , toggle_count [31:0] $end
$scope module dut $end
$var wire 1 " accepted_pulse $end
$var wire 1 # clear_pulse $end
$var wire 1 $ clk $end
$var wire 1 % fatal_error $end
$var wire 1 ' protocol_error_pulse $end
$var wire 1 ( rst_n $end
$var parameter 32 - CLK_HZ $end
$var parameter 32 . COMMAND_CYCLES $end
$var parameter 32 / COMMAND_MS $end
$var parameter 32 0 FATAL_HALF_CYCLES $end
$var parameter 32 1 FATAL_HALF_MS $end
$var parameter 32 2 PROTOCOL_CYCLES $end
$var parameter 32 3 PROTOCOL_MS $end
$var parameter 3 4 S_COMMAND $end
$var parameter 3 5 S_FATAL $end
$var parameter 3 6 S_IDLE $end
$var parameter 3 7 S_PROTO_OFF $end
$var parameter 3 8 S_PROTO_ON_1 $end
$var parameter 3 9 S_PROTO_ON_2 $end
$var reg 1 : fatal_latched $end
$var reg 1 ! led_pin $end
$var reg 3 ; state [2:0] $end
$var reg 32 < timer [31:0] $end
$upscope $end
$upscope $end
$enddefinitions $end
$comment Show the parameter values. $end
$dumpall
b100 9
b10 8
b11 7
b0 6
b101 5
b1 4
b10 3
b10 2
b10 1
b10 0
b100 /
b100 .
b1111101000 -
$end
#0
$dumpvars
bx <
bx ;
x:
b0 ,
b0 +
b0 *
bx )
0(
0'
0&
0%
0$
0#
0"
x!
$end
#5000
0!
0:
b0 <
b0 ;
1$
#10000
0$
#15000
1$
#20000
0$
#25000
1$
#30000
1(
0$
#35000
1$
#40000
0$
#45000
1$
#50000
1"
b0 )
0$
#55000
1!
b1 ;
1$
#60000
0"
0$
#65000
b1 <
1&
b1 ,
b1 +
1$
#70000
0$
#75000
b10 <
1$
#80000
0$
#85000
b11 <
1$
#90000
0$
#95000
0!
b0 <
b0 ;
1$
#100000
0$
#105000
0&
b10 ,
1$
#110000
0$
#115000
1$
#120000
0$
#125000
1$
#130000
0$
#135000
1$
#140000
1'
b1 )
0$
#145000
1!
b10 ;
1$
#150000
0'
0$
#155000
b1 <
1&
b11 ,
b10 +
1$
#160000
0$
#165000
0!
b0 <
b11 ;
1$
#170000
0$
#175000
b1 <
0&
b100 ,
1$
#180000
0$
#185000
1!
b0 <
b100 ;
1$
#190000
0$
#195000
b1 <
1&
b101 ,
b11 +
1$
#200000
0$
#205000
0!
b0 <
b0 ;
1$
#210000
0$
#215000
0&
b110 ,
1$
#220000
0$
#225000
1$
#230000
0$
#235000
1$
#240000
0$
#245000
1$
#250000
0$
#255000
1$
#260000
0$
#265000
1$
#270000
1%
b110 )
0$
#275000
b1 <
b101 ;
1:
1$
#280000
0%
0$
#285000
1!
b0 <
1$
#290000
0$
#295000
b1 <
1&
b111 ,
b100 +
1$
#300000
0$
#305000
0!
b0 <
1$
#310000
0$
#315000
b1 <
0&
b1000 ,
1$
#320000
0$
#325000
1!
b0 <
1$
#330000
0$
#335000
b1 <
1&
b1001 ,
b101 +
1$
#340000
0$
#345000
0!
b0 <
1$
#350000
0$
#355000
b1 <
0&
b1010 ,
1$
#360000
0$
#365000
1!
b0 <
1$
#370000
0$
#375000
b1 <
1&
b1011 ,
b110 +
1$
#380000
0$
#385000
0!
b0 <
1$
#390000
0$
#395000
b1 <
0&
b1100 ,
1$
#400000
1#
0$
#405000
0:
b0 <
b0 ;
1$
#410000
0#
0$
