final_project/fpga/rtl/dsp/mac_unit.v
module mac_unit (
  input wire                clk,
  input wire                rst_n,
  input wire                start,
  input wire                clear,
  input wire signed [15:0] operand_a_q88,
  input wire signed [15:0] operand_b_q88,
  output reg                done,
  output reg signed [31:0] accumulator_q1616,
  output reg signed [15:0] result_q88,
  output reg               overflow
);
  wire signed [31:0] product_q1616 = operand_a_q88 * operand_b_q88;
  wire signed [32:0] sum_ext =
    {accumulator_q1616[31], accumulator_q1616} +
    {product_q1616[31], product_q1616};

  reg signed [31:0] next_acc;
  reg next_overflow;
  reg signed [31:0] scaled_q88;

  always @(*) begin
    next_overflow = 1'b0;
    if (sum_ext > 33'sd2147483647) begin
      next_acc = 32'sh7fffffff;
      next_overflow = 1'b1;
    end else if (sum_ext < -33'sd2147483648) begin
      next_acc = 32'sh80000000;
      next_overflow = 1'b1;
    end else begin
      next_acc = sum_ext[31:0];
    end
    scaled_q88 = next_acc >>> 8;
  end

  function signed [15:0] saturate_q88;
    input signed [31:0] value;
    begin
      if (value > 32'sd32767)
        saturate_q88 = 16'sh7fff;
      else if (value < -32'sd32768)
        saturate_q88 = 16'sh8000;
      else
        saturate_q88 = value[15:0];
    end
  endfunction

  always @(posedge clk or negedge rst_n) begin
    if (!rst_n) begin
      done <= 1'b0;
      accumulator_q1616 <= 32'sd0;
      result_q88 <= 16'sd0;
      overflow <= 1'b0;
    end else begin
      done <= 1'b0;
      if (clear) begin
        accumulator_q1616 <= 32'sd0;
        result_q88 <= 16'sd0;
        overflow <= 1'b0;
      end else if (start) begin
        accumulator_q1616 <= next_acc;
        result_q88 <= saturate_q88(scaled_q88);
        overflow <= overflow | next_overflow;
        done <= 1'b1;
      end
    end
  end
endmodule

final_project/fpga/sim/tb_mac_unit.v
`timescale 1ns/1ps
module tb_mac_unit;
  reg clk = 1'b0;
  reg rst_n = 1'b0;
  reg start = 1'b0;
  reg clear = 1'b0;
  reg signed [15:0] a = 16'sd0;
  reg signed [15:0] b = 16'sd0;
  wire done;
  wire signed [31:0] acc;
  wire signed [15:0] result;
  wire overflow;
  integer failures = 0;

  always #5 clk = ~clk;
  mac_unit dut (
    .clk(clk), .rst_n(rst_n), .start(start), .clear(clear),
    .operand_a_q88(a), .operand_b_q88(b), .done(done),
    .accumulator_q1616(acc), .result_q88(result), .overflow(overflow)
  );

  task step;
    input signed [15:0] value_a;
    input signed [15:0] value_b;
    begin
      @(negedge clk); a = value_a; b = value_b; start = 1'b1;
      @(negedge clk); start = 1'b0;
      @(negedge clk);
    end
  endtask

  task expect_result;
    input signed [15:0] expected;
    begin
      if (result !== expected) begin
        $display("FALHA result=%0d esperado=%0d", result, expected);
        failures = failures + 1;
      end
    end
  endtask

  initial begin
    $dumpfile("build/tb_mac_unit.vcd");
    $dumpvars(0, tb_mac_unit);
    repeat (4) @(negedge clk);
    rst_n = 1'b1;
    step(16'sd256, 16'sd256); // 1.0 x 1.0
    expect_result(16'sd256);
    step(-16'sd256, 16'sd128); // soma -0.5
    expect_result(16'sd128);
    
    @(negedge clk); clear = 1'b1;
    @(negedge clk); clear = 1'b0;
    @(negedge clk);
    expect_result(16'sd0);

    step(16'sd32767, 16'sd32767);
    step(16'sd32767, 16'sd32767);
    step(16'sd32767, 16'sd32767);

    if (!overflow) begin
      $display("FALHA overflow nao ativou");
      failures = failures + 1;
    end

    if (failures == 0)
      $display("PASS tb_mac_unit");
    else
    $fatal(1, "FALHA tb_mac_unit: %0d erros", failures);
    $finish;
  end
endmodule

final_project/fpga/sim/build/tb_mac_unit.vcd
$date
	Mon Sep 28 19:06:48 2026
$end
$version
	Icarus Verilog
$end
$timescale
	1ps
$end
$scope module tb_mac_unit $end
$var wire 16 ! result [15:0] $end
$var wire 1 " overflow $end
$var wire 1 # done $end
$var wire 32 $ acc [31:0] $end
$var reg 16 % a [15:0] $end
$var reg 16 & b [15:0] $end
$var reg 1 ' clear $end
$var reg 1 ( clk $end
$var reg 1 ) rst_n $end
$var reg 1 * start $end
$var integer 32 + failures [31:0] $end
$scope module dut $end
$var wire 1 ' clear $end
$var wire 1 ( clk $end
$var wire 16 , operand_a_q88 [15:0] $end
$var wire 16 - operand_b_q88 [15:0] $end
$var wire 1 ) rst_n $end
$var wire 1 * start $end
$var wire 33 . sum_ext [32:0] $end
$var wire 32 / product_q1616 [31:0] $end
$var reg 32 0 accumulator_q1616 [31:0] $end
$var reg 1 # done $end
$var reg 32 1 next_acc [31:0] $end
$var reg 1 2 next_overflow $end
$var reg 1 " overflow $end
$var reg 16 3 result_q88 [15:0] $end
$var reg 32 4 scaled_q88 [31:0] $end
$scope function saturate_q88 $end
$var reg 32 5 value [31:0] $end
$upscope $end
$upscope $end
$scope task expect_result $end
$var reg 16 6 expected [15:0] $end
$upscope $end
$scope task step $end
$var reg 16 7 value_a [15:0] $end
$var reg 16 8 value_b [15:0] $end
$upscope $end
$upscope $end
$enddefinitions $end
$comment Show the parameter values. $end
$dumpall
$end
#0
$dumpvars
bx 8
bx 7
bx 6
bx 5
bx 4
bx 3
x2
bx 1
bx 0
b0 /
bx .
b0 -
b0 ,
b0 +
0*
0)
0(
0'
b0 &
b0 %
bx $
x#
x"
bx !
$end
#5000
b0 4
b0 1
02
b0 .
0"
b0 !
b0 3
b0 $
b0 0
0#
1(
#10000
0(
#15000
1(
#20000
0(
#25000
1(
#30000
0(
#35000
1(
#40000
b100000000 8
b100000000 7
1)
0(
#45000
1(
#50000
b100000000 4
b10000000000000000 1
1*
b10000000000000000 .
b10000000000000000 /
b100000000 &
b100000000 -
b100000000 %
b100000000 ,
0(
#55000
b1000000000 4
b100000000000000000 1
1#
b100000000 !
b100000000 3
b100000000000000000 .
b10000000000000000 $
b10000000000000000 0
b100000000 5
1(
#60000
0*
0(
#65000
0#
1(
#70000
b10000000 8
b1111111100000000 7
b100000000 6
0(
#75000
1(
#80000
b10000000 4
02
b1000000000000000 1
1*
b10000000 &
b10000000 -
b1000000000000000 .
b11111111111111111000000000000000 /
b1111111100000000 %
b1111111100000000 ,
0(
#85000
b0 4
b0 1
1#
b10000000 !
b10000000 3
b0 .
b1000000000000000 $
b1000000000000000 0
b10000000 5
1(
#90000
0*
0(
#95000
0#
1(
#100000
b10000000 6
0(
#105000
1(
#110000
1'
0(
#115000
b11111111111111111111111110000000 4
b11111111111111111000000000000000 1
b0 !
b0 3
b111111111111111111000000000000000 .
b0 $
b0 0
1(
#120000
0'
0(
#125000
1(
#130000
b111111111111111 8
b111111111111111 7
b0 6
0(
#135000
1(
#140000
b1111111111111100000000 4
02
b111111111111110000000000000001 1
1*
b111111111111111 &
b111111111111111 -
b111111111111110000000000000001 .
b111111111111110000000000000001 /
b111111111111111 %
b111111111111111 ,
0(
#145000
b11111111111111000000000 4
b1111111111111100000000000000010 1
1#
b111111111111111 !
b111111111111111 3
b1111111111111100000000000000010 .
b111111111111110000000000000001 $
b111111111111110000000000000001 0
b1111111111111100000000 5
1(
#150000
0*
0(
#155000
0#
1(
#160000
0(
#165000
1(
#170000
1*
0(
#175000
b11111111111111111111111 4
12
b1111111111111111111111111111111 1
1#
b10111111111111010000000000000011 .
b1111111111111100000000000000010 $
b1111111111111100000000000000010 0
b11111111111111000000000 5
1(
#180000
0*
0(
#185000
0#
1(
#190000
0(
#195000
1(
#200000
1*
0(
#205000
12
1#
1"
b10111111111111110000000000000000 .
b1111111111111111111111111111111 $
b1111111111111111111111111111111 0
b11111111111111111111111 5
1(
#210000
0*
0(
#215000
0#
1(
