final_project/fpga/gowin/src/pattern_stream.v
module pattern_stream #(
  parameter H_VISIBLE = 640,
  parameter V_VISIBLE = 480
)(
  input wire clk,
  input wire rst_n,
  input wire [1:0] mode,
  input wire [23:0] base_color,
  input wire signed [15:0] telemetry_sample,
  input wire [9:0] telemetry_count,
  output wire [9:0] telemetry_addr,
  output wire frame_start,
  output wire out_axis_tvalid,
  input wire out_axis_tready,
  output reg [23:0] out_axis_tdata,
  output wire [0:0] out_axis_tuser
  );
  reg [9:0] x;
  reg [8:0] y;
  reg [7:0] red;
  reg [7:0] green;
  reg [7:0] blue;
  reg signed [17:0] graph_y;

  assign out_axis_tvalid = rst_n;
  assign out_axis_tuser[0] = (x == 0) && (y == 0);
  assign frame_start = out_axis_tvalid && out_axis_tready && (x == 0) && (y == 0);
  assign telemetry_addr = x;

  always @(*) begin
    red = 8'd0;
    green = 8'd0;
    blue = 8'd0;
    graph_y = 18'sd240 - (telemetry_sample >>> 2);

    // O active_mode escolhe o conteudo principal do HDMI.
    case (mode)
      2'd0: begin
        if (x < 10'd80) begin red=8'hff; green=8'hff; blue=8'hff; end
        else if (x < 10'd160) begin red=8'hff; green=8'hff; blue=8'h00; end
        else if (x < 10'd240) begin red=8'h00; green=8'hff; blue=8'hff; end
        else if (x < 10'd320) begin red=8'h00; green=8'hff; blue=8'h00; end
        else if (x < 10'd400) begin red=8'hff; green=8'h00; blue=8'hff; end
        else if (x < 10'd480) begin red=8'hff; green=8'h00; blue=8'h00; end
        else if (x < 10'd560) begin red=8'h00; green=8'h00; blue=8'hff; end
        else begin red=8'h10; green=8'h10; blue=8'h10; end
      end

      2'd1: begin
        if (x[5] ^ y[5]) begin
          red = base_color[23:16];
          green = base_color[15:8];
          blue = base_color[7:0];
        end else begin
          red = ~base_color[23:16];
          green = ~base_color[15:8];
          blue = ~base_color[7:0];
        end
      end

      2'd2: begin
        red = x[7:0];
        green = y[7:0];
        blue = x[7:0] + y[7:0];
      end

      default: begin
        red = 8'h08;
        green = 8'h10;
        blue = 8'h18;

        if (y == 9'd240 || x == 10'd0) begin
          red = 8'h50;
          green = 8'h50;
          blue = 8'h50;
        end

        if (x < telemetry_count && graph_y >= 18'sd2 && graph_y <= 18'sd477 &&
          y >= graph_y - 18'sd2 && y <= graph_y + 18'sd2) begin
          red = 8'h20;
          green = 8'hff;
          blue = 8'h40;
        end
      end
    endcase

    // Indicador binario do active_mode no canto superior direito.
    // Quadrado esquerdo = mode[1], quadrado direito = mode[0].
    // Branco significa bit 1; cinza escuro significa bit 0.
    if (y < 9'd32 && x >= 10'd560 && x < 10'd592) begin
      if (mode[1]) begin
        red = 8'hff; green = 8'hff; blue = 8'hff;
      end else begin
        red = 8'h20; green = 8'h20; blue = 8'h20;
      end
    end

    if (y < 9'd32 && x >= 10'd600 && x < 10'd632) begin
      if (mode[0]) begin
        red = 8'hff; green = 8'hff; blue = 8'hff;
      end else begin
        red = 8'h20; green = 8'h20; blue = 8'h20;
      end
    end

    // SVO espera a ordem blue, green, red.
    out_axis_tdata = {blue, green, red};
  end

  always @(posedge clk or negedge rst_n) begin
    if (!rst_n) begin
      x <= 10'd0;
      y <= 9'd0;
    end else if (out_axis_tvalid && out_axis_tready) begin
      if (x == H_VISIBLE - 1) begin
        x <= 10'd0;
        if (y == V_VISIBLE - 1)
        y <= 9'd0;
        else
        y <= y + 1'b1;
      end else begin
        x <= x + 1'b1;
      end
    end
  end
endmodule

final_project/fpga/sim/tb_pattern_stream.v
`timescale 1ns/1ps
module tb_pattern_stream;
  reg clk = 1'b0;
  reg rst_n = 1'b0;
  reg [1:0] mode = 2'd0;
  reg ready = 1'b1;

  wire [9:0] telemetry_addr;
  wire frame_start;
  wire valid;
  wire [23:0] data;
  wire [0:0] user;

  integer failures = 0;
  integer starts = 0;

  always #5 clk = ~clk;

  pattern_stream #(.H_VISIBLE(640), .V_VISIBLE(2)) dut (
    .clk(clk), .rst_n(rst_n), .mode(mode), .base_color(24'h204080),
    .telemetry_sample(16'sd0), .telemetry_count(10'd0),
    .telemetry_addr(telemetry_addr), .frame_start(frame_start),
    .out_axis_tvalid(valid), .out_axis_tready(ready),
    .out_axis_tdata(data), .out_axis_tuser(user)
  );

  always @(posedge clk) begin
    if (valid && ready && user[0])
      starts = starts + 1;
  end

  task restart_frame;
    begin
      rst_n = 1'b0;
      repeat (2) @(negedge clk);
      rst_n = 1'b1;
    end
  endtask

  task expect_indicator;
    input [1:0] expected_mode;
    reg [23:0] expected_bit1;
    reg [23:0] expected_bit0;
    begin
      mode = expected_mode;
      restart_frame();

      expected_bit1 = expected_mode[1] ? 24'hffffff : 24'h202020;
      expected_bit0 = expected_mode[0] ? 24'hffffff : 24'h202020;

      while (!(dut.y == 0 && dut.x == 10'd565))
        @(negedge clk);
      if (data !== expected_bit1) begin
        $display("FALHA mode=%b indicador bit1 data=%h esperado=%h",
          expected_mode, data, expected_bit1);
        failures = failures + 1;
      end

      while (!(dut.y == 0 && dut.x == 10'd605))
        @(negedge clk);
      if (data !== expected_bit0) begin
        $display("FALHA mode=%b indicador bit0 data=%h esperado=%h",
          expected_mode, data, expected_bit0);
        failures = failures + 1;
      end
    end
  endtask

  initial begin
    $dumpfile("build/tb_pattern_stream.vcd");
    $dumpvars(0, tb_pattern_stream);

    expect_indicator(2'b00);
    expect_indicator(2'b01);
    expect_indicator(2'b10);
    expect_indicator(2'b11);

    if (starts < 4) begin
      $display("FALHA frame_start starts=%0d", starts);
      failures = failures + 1;
    end

    if (failures == 0)
      $display("PASS tb_pattern_stream: active_mode 00/01/10/11 visivel no HDMI");
    else
      $fatal(1, "FALHA tb_pattern_stream: %0d erros", failures);
    $finish;
  end
endmodule

final_project/fpga/sim/build/tb_pattern_stream.vcd
$date
	Mon Sep 28 19:08:23 2026
$end
$version
	Icarus Verilog
$end
$timescale
	1ps
$end
$scope module tb_pattern_stream $end
$var wire 1 ! valid $end
$var wire 1 " user $end
$var wire 10 # telemetry_addr [9:0] $end
$var wire 1 $ frame_start $end
$var wire 24 % data [23:0] $end
$var reg 1 & clk $end
$var reg 2 ' mode [1:0] $end
$var reg 1 ( ready $end
$var reg 1 ) rst_n $end
$var integer 32 * failures [31:0] $end
$var integer 32 + starts [31:0] $end
$scope module dut $end
$var wire 24 , base_color [23:0] $end
$var wire 1 & clk $end
$var wire 1 $ frame_start $end
$var wire 2 - mode [1:0] $end
$var wire 1 ( out_axis_tready $end
$var wire 1 " out_axis_tuser $end
$var wire 1 ! out_axis_tvalid $end
$var wire 1 ) rst_n $end
$var wire 10 . telemetry_addr [9:0] $end
$var wire 10 / telemetry_count [9:0] $end
$var wire 16 0 telemetry_sample [15:0] $end
$var parameter 32 1 H_VISIBLE $end
$var parameter 32 2 V_VISIBLE $end
$var reg 8 3 blue [7:0] $end
$var reg 18 4 graph_y [17:0] $end
$var reg 8 5 green [7:0] $end
$var reg 24 6 out_axis_tdata [23:0] $end
$var reg 8 7 red [7:0] $end
$var reg 10 8 x [9:0] $end
$var reg 9 9 y [8:0] $end
$upscope $end
$scope task expect_indicator $end
$var reg 24 : expected_bit0 [23:0] $end
$var reg 24 ; expected_bit1 [23:0] $end
$var reg 2 < expected_mode [1:0] $end
$upscope $end
$scope task restart_frame $end
$upscope $end
$upscope $end
$enddefinitions $end
$comment Show the parameter values. $end
$dumpall
b10 2
b1010000000 1
$end
#0
$dumpvars
b0 <
bx ;
bx :
bx 9
bx 8
b10000 7
b100000001000000010000 6
b10000 5
b11110000 4
b10000 3
b0 0
b0 /
bx .
b0 -
b1000000100000010000000 ,
b0 +
b0 *
0)
1(
b0 '
0&
b100000001000000010000 %
0$
bx #
x"
0!
$end
#5000
b111111111111111111111111 %
b111111111111111111111111 6
b11111111 3
b11111111 5
b11111111 7
1"
b0 9
b0 #
b0 .
b0 8
1&
#10000
0&
#15000
1&
#20000
1$
b1000000010000000100000 :
b1000000010000000100000 ;
1!
1)
0&
#25000
0$
b11111111 3
b11111111 5
b11111111 7
0"
b1 #
b1 .
b1 8
b1 +
1&
#30000
0&
#35000
b11111111 3
b11111111 5
b11111111 7
b10 #
b10 .
b10 8
1&
#40000
0&
#45000
b11111111 3
b11111111 5
b11111111 7
b11 #
b11 .
b11 8
1&
#50000
0&
#55000
b11111111 3
b11111111 5
b11111111 7
b100 #
b100 .
b100 8
1&
#60000
0&
#65000
b11111111 3
b11111111 5
b11111111 7
b101 #
b101 .
b101 8
1&
#70000
0&
#75000
b11111111 3
b11111111 5
b11111111 7
b110 #
b110 .
b110 8
1&
#80000
0&
#85000
b11111111 3
b11111111 5
b11111111 7
b111 #
b111 .
b111 8
1&
#90000
0&
#95000
b11111111 3
b11111111 5
b11111111 7
b1000 #
b1000 .
b1000 8
1&
#100000
0&
#105000
b11111111 3
b11111111 5
b11111111 7
b1001 #
b1001 .
b1001 8
1&
#110000
0&
#115000
b11111111 3
b11111111 5
b11111111 7
b1010 #
b1010 .
b1010 8
1&
#120000
0&
#125000
b11111111 3
b11111111 5
b11111111 7
b1011 #
b1011 .
b1011 8
1&
#130000
0&
#135000
b11111111 3
b11111111 5
b11111111 7
b1100 #
b1100 .
b1100 8
1&
#140000
0&
#145000
b11111111 3
b11111111 5
b11111111 7
b1101 #
b1101 .
b1101 8
1&
#150000
0&
#155000
b11111111 3
b11111111 5
b11111111 7
b1110 #
b1110 .
b1110 8
1&
#160000
0&
#165000
b11111111 3
b11111111 5
b11111111 7
b1111 #
b1111 .
b1111 8
1&
#170000
0&
#175000
b11111111 3
b11111111 5
b11111111 7
b10000 #
b10000 .
b10000 8
1&
#180000
0&
#185000
b11111111 3
b11111111 5
b11111111 7
b10001 #
b10001 .
b10001 8
1&
#190000
0&
#195000
b11111111 3
b11111111 5
b11111111 7
b10010 #
b10010 .
b10010 8
1&
#200000
0&
#205000
b11111111 3
b11111111 5
b11111111 7
b10011 #
b10011 .
b10011 8
1&
#210000
0&
#215000
b11111111 3
b11111111 5
b11111111 7
b10100 #
b10100 .
b10100 8
1&
#220000
0&
#225000
b11111111 3
b11111111 5
b11111111 7
b10101 #
b10101 .
b10101 8
1&
#230000
0&
#235000
b11111111 3
b11111111 5
b11111111 7
b10110 #
b10110 .
b10110 8
1&
#240000
0&
#245000
b11111111 3
b11111111 5
b11111111 7
b10111 #
b10111 .
b10111 8
1&
#250000
0&
#255000
b11111111 3
b11111111 5
b11111111 7
b11000 #
b11000 .
b11000 8
1&
#260000
0&
#265000
b11111111 3
b11111111 5
b11111111 7
b11001 #
b11001 .
b11001 8
1&
#270000
0&
#275000
b11111111 3
b11111111 5
b11111111 7
b11010 #
b11010 .
b11010 8
1&
#280000
0&
#285000
b11111111 3
b11111111 5
b11111111 7
b11011 #
b11011 .
b11011 8
1&
#290000
0&
#295000
b11111111 3
b11111111 5
b11111111 7
b11100 #
b11100 .
b11100 8
1&
#300000
0&
#305000
b11111111 3
b11111111 5
b11111111 7
b11101 #
b11101 .
b11101 8
1&
#310000
0&
#315000
b11111111 3
b11111111 5
b11111111 7
b11110 #
b11110 .
b11110 8
1&
#320000
0&
#325000
b11111111 3
b11111111 5
b11111111 7
b11111 #
b11111 .
b11111 8
1&
#330000
0&
#335000
b11111111 3
b11111111 5
b11111111 7
b100000 #
b100000 .
b100000 8
1&
#340000
0&
#345000
b11111111 3
b11111111 5
b11111111 7
b100001 #
b100001 .
b100001 8
1&
#350000
0&
#355000
b11111111 3
b11111111 5
b11111111 7
b100010 #
b100010 .
b100010 8
1&
#360000
0&
#365000
b11111111 3
b11111111 5
b11111111 7
b100011 #
b100011 .
b100011 8
1&
#370000
0&
#375000
b11111111 3
b11111111 5
b11111111 7
b100100 #
b100100 .
b100100 8
1&
#380000
0&
#385000
b11111111 3
b11111111 5
b11111111 7
b100101 #
b100101 .
b100101 8
1&
#390000
0&
#395000
b11111111 3
b11111111 5
b11111111 7
b100110 #
b100110 .
b100110 8
1&
#400000
0&
#405000
b11111111 3
b11111111 5
b11111111 7
b100111 #
b100111 .
b100111 8
1&
#410000
0&
#415000
b11111111 3
b11111111 5
b11111111 7
b101000 #
b101000 .
b101000 8
1&
#420000
0&
#425000
b11111111 3
b11111111 5
b11111111 7
b101001 #
b101001 .
b101001 8
1&
#430000
0&
#435000
b11111111 3
b11111111 5
b11111111 7
b101010 #
b101010 .
b101010 8
1&
#440000
0&
#445000
b11111111 3
b11111111 5
b11111111 7
b101011 #
b101011 .
b101011 8
1&
#450000
0&
#455000
b11111111 3
b11111111 5
b11111111 7
b101100 #
b101100 .
b101100 8
1&
#460000
0&
#465000
b11111111 3
b11111111 5
b11111111 7
b101101 #
b101101 .
b101101 8
1&
#470000
0&
#475000
b11111111 3
b11111111 5
b11111111 7
b101110 #
b101110 .
b101110 8
1&
#480000
0&
#485000
b11111111 3
b11111111 5
b11111111 7
b101111 #
b101111 .
b101111 8
1&
#490000
0&
#495000
b11111111 3
b11111111 5
b11111111 7
b110000 #
b110000 .
b110000 8
1&
#500000
0&
#505000
b11111111 3
b11111111 5
b11111111 7
b110001 #
b110001 .
b110001 8
1&
#510000
0&
#515000
b11111111 3
b11111111 5
b11111111 7
b110010 #
b110010 .
b110010 8
1&
#520000
0&
#525000
b11111111 3
b11111111 5
b11111111 7
b110011 #
b110011 .
b110011 8
1&
#530000
0&
#535000
b11111111 3
b11111111 5
b11111111 7
b110100 #
b110100 .
b110100 8
1&
#540000
0&
#545000
b11111111 3
b11111111 5
b11111111 7
b110101 #
b110101 .
b110101 8
1&
#550000
0&
#555000
b11111111 3
b11111111 5
b11111111 7
b110110 #
b110110 .
b110110 8
1&
#560000
0&
#565000
b11111111 3
b11111111 5
b11111111 7
b110111 #
b110111 .
b110111 8
1&
#570000
0&
#575000
b11111111 3
b11111111 5
b11111111 7
b111000 #
b111000 .
b111000 8
1&
#580000
0&
#585000
b11111111 3
b11111111 5
b11111111 7
b111001 #
b111001 .
b111001 8
1&
#590000
0&
#595000
b11111111 3
b11111111 5
b11111111 7
b111010 #
b111010 .
b111010 8
1&
#600000
0&
#605000
b11111111 3
b11111111 5
b11111111 7
b111011 #
b111011 .
b111011 8
1&
#610000
0&
#615000
b11111111 3
b11111111 5
b11111111 7
b111100 #
b111100 .
b111100 8
1&
#620000
0&
#625000
b11111111 3
b11111111 5
b11111111 7
b111101 #
b111101 .
b111101 8
1&
#630000
0&
#635000
b11111111 3
b11111111 5
b11111111 7
b111110 #
b111110 .
b111110 8
1&
#640000
0&
#645000
b11111111 3
b11111111 5
b11111111 7
b111111 #
b111111 .
b111111 8
1&
#650000
0&
#655000
b11111111 3
b11111111 5
b11111111 7
b1000000 #
b1000000 .
b1000000 8
1&
#660000
0&
#665000
b11111111 3
b11111111 5
b11111111 7
b1000001 #
b1000001 .
b1000001 8
1&
#670000
0&
#675000
b11111111 3
b11111111 5
b11111111 7
b1000010 #
b1000010 .
b1000010 8
1&
#680000
0&
#685000
b11111111 3
b11111111 5
b11111111 7
b1000011 #
b1000011 .
b1000011 8
1&
#690000
0&
#695000
b11111111 3
b11111111 5
b11111111 7
b1000100 #
b1000100 .
b1000100 8
1&
#700000
0&
#705000
b11111111 3
b11111111 5
b11111111 7
b1000101 #
b1000101 .
b1000101 8
1&
#710000
0&
#715000
b11111111 3
b11111111 5
b11111111 7
b1000110 #
b1000110 .
b1000110 8
1&
#720000
0&
#725000
b11111111 3
b11111111 5
b11111111 7
b1000111 #
b1000111 .
b1000111 8
1&
#730000
0&
#735000
b11111111 3
b11111111 5
b11111111 7
b1001000 #
b1001000 .
b1001000 8
1&
#740000
0&
#745000
b11111111 3
b11111111 5
b11111111 7
b1001001 #
b1001001 .
b1001001 8
1&
#750000
0&
#755000
b11111111 3
b11111111 5
b11111111 7
b1001010 #
b1001010 .
b1001010 8
1&
#760000
0&
#765000
b11111111 3
b11111111 5
b11111111 7
b1001011 #
b1001011 .
b1001011 8
1&
#770000
0&
#775000
b11111111 3
b11111111 5
b11111111 7
b1001100 #
b1001100 .
b1001100 8
1&
#780000
0&
#785000
b11111111 3
b11111111 5
b11111111 7
b1001101 #
b1001101 .
b1001101 8
1&
#790000
0&
#795000
b11111111 3
b11111111 5
b11111111 7
b1001110 #
b1001110 .
b1001110 8
1&
#800000
0&
#805000
b11111111 3
b11111111 5
b11111111 7
b1001111 #
b1001111 .
b1001111 8
1&
#810000
0&
#815000
b1111111111111111 %
b1111111111111111 6
b0 3
b11111111 5
b11111111 7
b1010000 #
b1010000 .
b1010000 8
1&
#820000
0&
#825000
b11111111 5
b11111111 7
b1010001 #
b1010001 .
b1010001 8
1&
#830000
0&
#835000
b11111111 5
b11111111 7
b1010010 #
b1010010 .
b1010010 8
1&
#840000
0&
#845000
b11111111 5
b11111111 7
b1010011 #
b1010011 .
b1010011 8
1&
#850000
0&
#855000
b11111111 5
b11111111 7
b1010100 #
b1010100 .
b1010100 8
1&
#860000
0&
#865000
b11111111 5
b11111111 7
b1010101 #
b1010101 .
b1010101 8
1&
#870000
0&
#875000
b11111111 5
b11111111 7
b1010110 #
b1010110 .
b1010110 8
1&
#880000
0&
#885000
b11111111 5
b11111111 7
b1010111 #
b1010111 .
b1010111 8
1&
#890000
0&
#895000
b11111111 5
b11111111 7
b1011000 #
b1011000 .
b1011000 8
1&
#900000
0&
#905000
b11111111 5
b11111111 7
b1011001 #
b1011001 .
b1011001 8
1&
#910000
0&
#915000
b11111111 5
b11111111 7
b1011010 #
b1011010 .
b1011010 8
1&
#920000
0&
#925000
b11111111 5
b11111111 7
b1011011 #
b1011011 .
b1011011 8
1&
#930000
0&
#935000
b11111111 5
b11111111 7
b1011100 #
b1011100 .
b1011100 8
1&
#940000
0&
#945000
b11111111 5
b11111111 7
b1011101 #
b1011101 .
b1011101 8
1&
#950000
0&
#955000
b11111111 5
b11111111 7
b1011110 #
b1011110 .
b1011110 8
1&
#960000
0&
#965000
b11111111 5
b11111111 7
b1011111 #
b1011111 .
b1011111 8
1&
#970000
0&
#975000
b11111111 5
b11111111 7
b1100000 #
b1100000 .
b1100000 8
1&
#980000
0&
#985000
b11111111 5
b11111111 7
b1100001 #
b1100001 .
b1100001 8
1&
#990000
0&
#995000
b11111111 5
b11111111 7
b1100010 #
b1100010 .
b1100010 8
1&
#1000000
0&
#1005000
b11111111 5
b11111111 7
b1100011 #
b1100011 .
b1100011 8
1&
#1010000
0&
#1015000
b11111111 5
b11111111 7
b1100100 #
b1100100 .
b1100100 8
1&
#1020000
0&
#1025000
b11111111 5
b11111111 7
b1100101 #
b1100101 .
b1100101 8
1&
#1030000
0&
#1035000
b11111111 5
b11111111 7
b1100110 #
b1100110 .
b1100110 8
1&
#1040000
0&
#1045000
b11111111 5
b11111111 7
b1100111 #
b1100111 .
b1100111 8
1&
#1050000
0&
#1055000
b11111111 5
b11111111 7
b1101000 #
b1101000 .
b1101000 8
1&
#1060000
0&
#1065000
b11111111 5
b11111111 7
b1101001 #
b1101001 .
b1101001 8
1&
#1070000
0&
#1075000
b11111111 5
b11111111 7
b1101010 #
b1101010 .
b1101010 8
1&
#1080000
0&
#1085000
b11111111 5
b11111111 7
b1101011 #
b1101011 .
b1101011 8
1&
#1090000
0&
#1095000
b11111111 5
b11111111 7
b1101100 #
b1101100 .
b1101100 8
1&
#1100000
0&
#1105000
b11111111 5
b11111111 7
b1101101 #
b1101101 .
b1101101 8
1&
#1110000
0&
#1115000
b11111111 5
b11111111 7
b1101110 #
b1101110 .
b1101110 8
1&
#1120000
0&
#1125000
b11111111 5
b11111111 7
b1101111 #
b1101111 .
b1101111 8
1&
#1130000
0&
#1135000
b11111111 5
b11111111 7
b1110000 #
b1110000 .
b1110000 8
1&
#1140000
0&
#1145000
b11111111 5
b11111111 7
b1110001 #
b1110001 .
b1110001 8
1&
#1150000
0&
#1155000
b11111111 5
b11111111 7
b1110010 #
b1110010 .
b1110010 8
1&
#1160000
0&
#1165000
b11111111 5
b11111111 7
b1110011 #
b1110011 .
b1110011 8
1&
#1170000
0&
#1175000
b11111111 5
b11111111 7
b1110100 #
b1110100 .
b1110100 8
1&
#1180000
0&
#1185000
b11111111 5
b11111111 7
b1110101 #
b1110101 .
b1110101 8
1&
#1190000
0&
#1195000
b11111111 5
b11111111 7
b1110110 #
b1110110 .
b1110110 8
1&
#1200000
0&
#1205000
b11111111 5
b11111111 7
b1110111 #
b1110111 .
b1110111 8
1&
#1210000
0&
#1215000
b11111111 5
b11111111 7
b1111000 #
b1111000 .
b1111000 8
1&
#1220000
0&
#1225000
b11111111 5
b11111111 7
b1111001 #
b1111001 .
b1111001 8
1&
#1230000
0&
#1235000
b11111111 5
b11111111 7
b1111010 #
b1111010 .
b1111010 8
1&
#1240000
0&
#1245000
b11111111 5
b11111111 7
b1111011 #
b1111011 .
b1111011 8
1&
#1250000
0&
#1255000
b11111111 5
b11111111 7
b1111100 #
b1111100 .
b1111100 8
1&
#1260000
0&
#1265000
b11111111 5
b11111111 7
b1111101 #
b1111101 .
b1111101 8
1&
#1270000
0&
#1275000
b11111111 5
b11111111 7
b1111110 #
b1111110 .
b1111110 8
1&
#1280000
0&
#1285000
b11111111 5
b11111111 7
b1111111 #
b1111111 .
b1111111 8
1&
#1290000
0&
#1295000
b11111111 5
b11111111 7
b10000000 #
b10000000 .
b10000000 8
1&
#1300000
0&
#1305000
b11111111 5
b11111111 7
b10000001 #
b10000001 .
b10000001 8
1&
#1310000
0&
#1315000
b11111111 5
b11111111 7
b10000010 #
b10000010 .
b10000010 8
1&
#1320000
0&
#1325000
b11111111 5
b11111111 7
b10000011 #
b10000011 .
b10000011 8
1&
#1330000
0&
#1335000
b11111111 5
b11111111 7
b10000100 #
b10000100 .
b10000100 8
1&
#1340000
0&
#1345000
b11111111 5
b11111111 7
b10000101 #
b10000101 .
b10000101 8
1&
#1350000
0&
#1355000
b11111111 5
b11111111 7
b10000110 #
b10000110 .
b10000110 8
1&
#1360000
0&
#1365000
b11111111 5
b11111111 7
b10000111 #
b10000111 .
b10000111 8
1&
#1370000
0&
#1375000
b11111111 5
b11111111 7
b10001000 #
b10001000 .
b10001000 8
1&
#1380000
0&
#1385000
b11111111 5
b11111111 7
b10001001 #
b10001001 .
b10001001 8
1&
#1390000
0&
#1395000
b11111111 5
b11111111 7
b10001010 #
b10001010 .
b10001010 8
1&
#1400000
0&
#1405000
b11111111 5
b11111111 7
b10001011 #
b10001011 .
b10001011 8
1&
#1410000
0&
#1415000
b11111111 5
b11111111 7
b10001100 #
b10001100 .
b10001100 8
1&
#1420000
0&
#1425000
b11111111 5
b11111111 7
b10001101 #
b10001101 .
b10001101 8
1&
#1430000
0&
#1435000
b11111111 5
b11111111 7
b10001110 #
b10001110 .
b10001110 8
1&
#1440000
0&
#1445000
b11111111 5
b11111111 7
b10001111 #
b10001111 .
b10001111 8
1&
#1450000
0&
#1455000
b11111111 5
b11111111 7
b10010000 #
b10010000 .
b10010000 8
1&
#1460000
0&
#1465000
b11111111 5
b11111111 7
b10010001 #
b10010001 .
b10010001 8
1&
#1470000
0&
#1475000
b11111111 5
b11111111 7
b10010010 #
b10010010 .
b10010010 8
1&
#1480000
0&
#1485000
b11111111 5
b11111111 7
b10010011 #
b10010011 .
b10010011 8
1&
#1490000
0&
#1495000
b11111111 5
b11111111 7
b10010100 #
b10010100 .
b10010100 8
1&
#1500000
0&
#1505000
b11111111 5
b11111111 7
b10010101 #
b10010101 .
b10010101 8
1&
#1510000
0&
#1515000
b11111111 5
b11111111 7
b10010110 #
b10010110 .
b10010110 8
1&
#1520000
0&
#1525000
b11111111 5
b11111111 7
b10010111 #
b10010111 .
b10010111 8
1&
#1530000
0&
#1535000
b11111111 5
b11111111 7
b10011000 #
b10011000 .
b10011000 8
1&
#1540000
0&
#1545000
b11111111 5
b11111111 7
b10011001 #
b10011001 .
b10011001 8
1&
#1550000
0&
#1555000
b11111111 5
b11111111 7
b10011010 #
b10011010 .
b10011010 8
1&
#1560000
0&
#1565000
b11111111 5
b11111111 7
b10011011 #
b10011011 .
b10011011 8
1&
#1570000
0&
#1575000
b11111111 5
b11111111 7
b10011100 #
b10011100 .
b10011100 8
1&
#1580000
0&
#1585000
b11111111 5
b11111111 7
b10011101 #
b10011101 .
b10011101 8
1&
#1590000
0&
#1595000
b11111111 5
b11111111 7
b10011110 #
b10011110 .
b10011110 8
1&
#1600000
0&
#1605000
b11111111 5
b11111111 7
b10011111 #
b10011111 .
b10011111 8
1&
#1610000
0&
#1615000
b111111111111111100000000 %
b111111111111111100000000 6
b11111111 3
b11111111 5
b0 7
b10100000 #
b10100000 .
b10100000 8
1&
#1620000
0&
#1625000
b11111111 3
b11111111 5
b10100001 #
b10100001 .
b10100001 8
1&
#1630000
0&
#1635000
b11111111 3
b11111111 5
b10100010 #
b10100010 .
b10100010 8
1&
#1640000
0&
#1645000
b11111111 3
b11111111 5
b10100011 #
b10100011 .
b10100011 8
1&
#1650000
0&
#1655000
b11111111 3
b11111111 5
b10100100 #
b10100100 .
b10100100 8
1&
#1660000
0&
#1665000
b11111111 3
b11111111 5
b10100101 #
b10100101 .
b10100101 8
1&
#1670000
0&
#1675000
b11111111 3
b11111111 5
b10100110 #
b10100110 .
b10100110 8
1&
#1680000
0&
#1685000
b11111111 3
b11111111 5
b10100111 #
b10100111 .
b10100111 8
1&
#1690000
0&
#1695000
b11111111 3
b11111111 5
b10101000 #
b10101000 .
b10101000 8
1&
#1700000
0&
#1705000
b11111111 3
b11111111 5
b10101001 #
b10101001 .
b10101001 8
1&
#1710000
0&
#1715000
b11111111 3
b11111111 5
b10101010 #
b10101010 .
b10101010 8
1&
#1720000
0&
#1725000
b11111111 3
b11111111 5
b10101011 #
b10101011 .
b10101011 8
1&
#1730000
0&
#1735000
b11111111 3
b11111111 5
b10101100 #
b10101100 .
b10101100 8
1&
#1740000
0&
#1745000
b11111111 3
b11111111 5
b10101101 #
b10101101 .
b10101101 8
1&
#1750000
0&
#1755000
b11111111 3
b11111111 5
b10101110 #
b10101110 .
b10101110 8
1&
#1760000
0&
#1765000
b11111111 3
b11111111 5
b10101111 #
b10101111 .
b10101111 8
1&
#1770000
0&
#1775000
b11111111 3
b11111111 5
b10110000 #
b10110000 .
b10110000 8
1&
#1780000
0&
#1785000
b11111111 3
b11111111 5
b10110001 #
b10110001 .
b10110001 8
1&
#1790000
0&
#1795000
b11111111 3
b11111111 5
b10110010 #
b10110010 .
b10110010 8
1&
#1800000
0&
#1805000
b11111111 3
b11111111 5
b10110011 #
b10110011 .
b10110011 8
1&
#1810000
0&
#1815000
b11111111 3
b11111111 5
b10110100 #
b10110100 .
b10110100 8
1&
#1820000
0&
#1825000
b11111111 3
b11111111 5
b10110101 #
b10110101 .
b10110101 8
1&
#1830000
0&
#1835000
b11111111 3
b11111111 5
b10110110 #
b10110110 .
b10110110 8
1&
#1840000
0&
#1845000
b11111111 3
b11111111 5
b10110111 #
b10110111 .
b10110111 8
1&
#1850000
0&
#1855000
b11111111 3
b11111111 5
b10111000 #
b10111000 .
b10111000 8
1&
#1860000
0&
#1865000
b11111111 3
b11111111 5
b10111001 #
b10111001 .
b10111001 8
1&
#1870000
0&
#1875000
b11111111 3
b11111111 5
b10111010 #
b10111010 .
b10111010 8
1&
#1880000
0&
#1885000
b11111111 3
b11111111 5
b10111011 #
b10111011 .
b10111011 8
1&
#1890000
0&
#1895000
b11111111 3
b11111111 5
b10111100 #
b10111100 .
b10111100 8
1&
#1900000
0&
#1905000
b11111111 3
b11111111 5
b10111101 #
b10111101 .
b10111101 8
1&
#1910000
0&
#1915000
b11111111 3
b11111111 5
b10111110 #
b10111110 .
b10111110 8
1&
#1920000
0&
#1925000
b11111111 3
b11111111 5
b10111111 #
b10111111 .
b10111111 8
1&
#1930000
0&
#1935000
b11111111 3
b11111111 5
b11000000 #
b11000000 .
b11000000 8
1&
#1940000
0&
#1945000
b11111111 3
b11111111 5
b11000001 #
b11000001 .
b11000001 8
1&
#1950000
0&
#1955000
b11111111 3
b11111111 5
b11000010 #
b11000010 .
b11000010 8
1&
#1960000
0&
#1965000
b11111111 3
b11111111 5
b11000011 #
b11000011 .
b11000011 8
1&
#1970000
0&
#1975000
b11111111 3
b11111111 5
b11000100 #
b11000100 .
b11000100 8
1&
#1980000
0&
#1985000
b11111111 3
b11111111 5
b11000101 #
b11000101 .
b11000101 8
1&
#1990000
0&
#1995000
b11111111 3
b11111111 5
b11000110 #
b11000110 .
b11000110 8
1&
#2000000
0&
#2005000
b11111111 3
b11111111 5
b11000111 #
b11000111 .
b11000111 8
1&
#2010000
0&
#2015000
b11111111 3
b11111111 5
b11001000 #
b11001000 .
b11001000 8
1&
#2020000
0&
#2025000
b11111111 3
b11111111 5
b11001001 #
b11001001 .
b11001001 8
1&
#2030000
0&
#2035000
b11111111 3
b11111111 5
b11001010 #
b11001010 .
b11001010 8
1&
#2040000
0&
#2045000
b11111111 3
b11111111 5
b11001011 #
b11001011 .
b11001011 8
1&
#2050000
0&
#2055000
b11111111 3
b11111111 5
b11001100 #
b11001100 .
b11001100 8
1&
#2060000
0&
#2065000
b11111111 3
b11111111 5
b11001101 #
b11001101 .
b11001101 8
1&
#2070000
0&
#2075000
b11111111 3
b11111111 5
b11001110 #
b11001110 .
b11001110 8
1&
#2080000
0&
#2085000
b11111111 3
b11111111 5
b11001111 #
b11001111 .
b11001111 8
1&
#2090000
0&
#2095000
b11111111 3
b11111111 5
b11010000 #
b11010000 .
b11010000 8
1&
#2100000
0&
#2105000
b11111111 3
b11111111 5
b11010001 #
b11010001 .
b11010001 8
1&
#2110000
0&
#2115000
b11111111 3
b11111111 5
b11010010 #
b11010010 .
b11010010 8
1&
#2120000
0&
#2125000
b11111111 3
b11111111 5
b11010011 #
b11010011 .
b11010011 8
1&
#2130000
0&
