final_project/fpga/rtl/control/uart_rx.v
module uart_rx #(
  parameter integer CLKS_PER_BIT = 219
)(
  input wire clk,
  input wire rst_n,
  input wire rx,
  output reg data_valid,
  output reg [7:0] data_byte,
  output reg framing_error
);
  localparam S_IDLE = 3'd0;
  localparam S_START = 3'd1;
  localparam S_DATA = 3'd2;
  localparam S_STOP = 3'd3;

  localparam COUNT_W = $clog2(CLKS_PER_BIT + 1);
  reg [2:0] state;
  reg [COUNT_W-1:0] clock_count;
  reg [2:0] bit_index;
  reg [7:0] shift;
  reg rx_meta;
  reg rx_sync;

  always @(posedge clk or negedge rst_n) begin
    if (!rst_n) begin
      rx_meta <= 1'b1;
      rx_sync <= 1'b1;
    end else begin
      rx_meta <= rx;
      rx_sync <= rx_meta;
    end
  end

  always @(posedge clk or negedge rst_n) begin
    if (!rst_n) begin
      state <= S_IDLE;
      clock_count <= {COUNT_W{1'b0}};
      bit_index <= 3'd0;
      shift <= 8'd0;
      data_valid <= 1'b0;
      data_byte <= 8'd0;
      framing_error <= 1'b0;
    end else begin
      data_valid <= 1'b0;
      framing_error <= 1'b0;
      case (state)
        S_IDLE: begin
          clock_count <= {COUNT_W{1'b0}};
            if (!rx_sync)
            state <= S_START;
        end
        S_START: begin
          if (clock_count == (CLKS_PER_BIT / 2) - 1) begin
            clock_count <= {COUNT_W{1'b0}};
            if (!rx_sync) begin
              bit_index <= 3'd0;
              state <= S_DATA;
            end else begin
              state <= S_IDLE;
            end
          end else begin
            clock_count <= clock_count + 1'b1;
          end
        end
        S_DATA: begin
          if (clock_count == CLKS_PER_BIT - 1) begin
            clock_count <= {COUNT_W{1'b0}};
            shift[bit_index] <= rx_sync;
            if (bit_index == 3'd7)
              state <= S_STOP;
            else
              bit_index <= bit_index + 1'b1;
          end else begin
            clock_count <= clock_count + 1'b1;
          end
        end
        S_STOP: begin
          if (clock_count == CLKS_PER_BIT - 1) begin
            clock_count <= {COUNT_W{1'b0}};
            if (rx_sync) begin
              data_byte <= shift;
              data_valid <= 1'b1;
            end else begin
              framing_error <= 1'b1;
            end
            state <= S_IDLE;
          end else begin
            clock_count <= clock_count + 1'b1;
          end
        end
        default: state <= S_IDLE;
      endcase
    end
  end
endmodule

final_project/fpga/sim/tb_uart_stress.v
`timescale 1ns/1ps
// Teste unitario de UART RX: 256 bytes, stop bit invalido e falso start.
// Compilar a partir de final_project/fpga/sim.
module tb_uart_stress;
    localparam integer CLKS_PER_BIT = 16;
    reg clk = 1'b0;
    reg rst_n = 1'b0;
    reg rx = 1'b1;
    wire data_valid;
    wire [7:0] data_byte;
    wire framing_error;
    integer received = 0;
    integer framing_errors = 0;
    reg [7:0] last_byte;
    integer i;
    integer previous;
    integer old_errors;

    always #5 clk = ~clk;

    uart_rx #(.CLKS_PER_BIT(CLKS_PER_BIT)) dut (
        .clk(clk), .rst_n(rst_n), .rx(rx),
        .data_valid(data_valid), .data_byte(data_byte),
        .framing_error(framing_error)
    );

    always @(posedge clk) begin
        if (rst_n) begin
            if (data_valid) begin
                received = received + 1;
                last_byte = data_byte;
            end
            if (framing_error)
                framing_errors = framing_errors + 1;
        end
    end

    task send_uart_byte;
        input [7:0] value;
        input good_stop;
        integer b;
        begin
            @(negedge clk); rx = 1'b0; // start
            repeat (CLKS_PER_BIT) @(negedge clk);
            for (b=0; b<8; b=b+1) begin
                rx = value[b];
                repeat (CLKS_PER_BIT) @(negedge clk);
            end
            rx = good_stop; // forcar erro fisico no stop bit, se 0
            repeat (CLKS_PER_BIT) @(negedge clk);
            rx = 1'b1;
            repeat (CLKS_PER_BIT*2) @(negedge clk);
        end
    endtask

    task check_byte;
        input [7:0] value;
        begin
            previous = received;
            send_uart_byte(value, 1'b1);
            repeat (3) @(negedge clk);
            if ((received != previous + 1) || (last_byte !== value))
                $fatal(1, "FAIL UART byte=%h recebido=%h delta=%0d", value, last_byte, received-previous);
        end
    endtask

    initial begin
        $dumpfile("build/tb_uart_stress.vcd");
        $dumpvars(0,tb_uart_stress);
        repeat (8) @(negedge clk);
        rst_n = 1'b1;
        repeat (8) @(negedge clk);

        // Exaustivo no espaco pequeno: cada byte possivel.
        for (i=0; i<256; i=i+1)
            check_byte(i[7:0]);
        $display("PASS UART: 256 valores de byte recebidos");

        // Start falso: duracao muito menor do que meio bit.
        previous = received;
        @(negedge clk); rx = 1'b0;
        repeat (2) @(negedge clk);
        rx = 1'b1;
        repeat (CLKS_PER_BIT*3) @(negedge clk);
        if (received != previous)
            $fatal(1,"FAIL UART falso start gerou byte");
        $display("PASS UART: pulso de falso start ignorado");

        // Stop errado: DEVE detectar framing_error, sem entregar byte.
        previous = received;
        old_errors = framing_errors;
        send_uart_byte(8'h55,1'b0);
        repeat (3) @(negedge clk);
        if (received != previous || framing_errors != old_errors+1)
            $fatal(1,"FAIL UART stop: recebidos=%0d erro_delta=%0d", received-previous,framing_errors-old_errors);
        $display("PASS UART: stop bit invalido detectado");

        // O receptor precisa continuar funcionando depois do erro.
        check_byte(8'hA5);
        $display("PASS UART: recuperou-se do stop bit invalido");
        $display("PASS tb_uart_stress: bytes_validos=%0d framing_errors=%0d", received, framing_errors);
        $finish;
    end
endmodule

final_project/fpga/sim/build/tb_uart_stress.vcd
$date
	Fri Oct  9 19:27:57 2026
$end
$version
	Icarus Verilog
$end
$timescale
	1ps
$end
$scope module tb_uart_stress $end
$var wire 1 ! framing_error $end
$var wire 1 " data_valid $end
$var wire 8 # data_byte [7:0] $end
$var parameter 32 $ CLKS_PER_BIT $end
$var reg 1 % clk $end
$var reg 8 & last_byte [7:0] $end
$var reg 1 ' rst_n $end
$var reg 1 ( rx $end
$var integer 32 ) framing_errors [31:0] $end
$var integer 32 * i [31:0] $end
$var integer 32 + old_errors [31:0] $end
$var integer 32 , previous [31:0] $end
$var integer 32 - received [31:0] $end
$scope module dut $end
$var wire 1 % clk $end
$var wire 1 ' rst_n $end
$var wire 1 ( rx $end
$var parameter 32 . CLKS_PER_BIT $end
$var parameter 32 / COUNT_W $end
$var parameter 3 0 S_DATA $end
$var parameter 3 1 S_IDLE $end
$var parameter 3 2 S_START $end
$var parameter 3 3 S_STOP $end
$var reg 3 4 bit_index [2:0] $end
$var reg 5 5 clock_count [4:0] $end
$var reg 8 6 data_byte [7:0] $end
$var reg 1 " data_valid $end
$var reg 1 ! framing_error $end
$var reg 1 7 rx_meta $end
$var reg 1 8 rx_sync $end
$var reg 8 9 shift [7:0] $end
$var reg 3 : state [2:0] $end
$upscope $end
$scope task check_byte $end
$var reg 8 ; value [7:0] $end
$upscope $end
$scope task send_uart_byte $end
$var reg 1 < good_stop $end
$var reg 8 = value [7:0] $end
$var integer 32 > b [31:0] $end
$upscope $end
$upscope $end
$enddefinitions $end
$comment Show the parameter values. $end
$dumpall
b11 3
b1 2
b0 1
b10 0
b101 /
b10000 .
b10000 $
$end
#0
$dumpvars
bx >
bx =
x<
bx ;
bx :
bx 9
x8
x7
bx 6
bx 5
bx 4
b0 -
bx ,
bx +
bx *
b0 )
1(
0'
bx &
0%
bx #
x"
x!
$end
#5000
18
17
0!
b0 #
b0 6
0"
b0 9
b0 4
b0 5
b0 :
1%
#10000
0%
#15000
1%
#20000
0%
#25000
1%
#30000
0%
#35000
1%
#40000
0%
#45000
1%
#50000
0%
#55000
1%
#60000
0%
#65000
1%
#70000
0%
#75000
1%
#80000
1'
0%
#85000
1%
#90000
0%
#95000
1%
#100000
0%
#105000
1%
#110000
0%
#115000
1%
#120000
0%
#125000
1%
#130000
0%
#135000
1%
#140000
0%
#145000
1%
#150000
0%
#155000
1%
#160000
1<
b0 =
b0 ,
b0 ;
b0 *
0%
#165000
1%
#170000
0(
0%
#175000
07
1%
#180000
0%
#185000
08
1%
#190000
0%
#195000
b1 :
1%
#200000
0%
#205000
b1 5
1%
#210000
0%
#215000
b10 5
1%
#220000
0%
#225000
b11 5
1%
#230000
0%
#235000
b100 5
1%
#240000
0%
#245000
b101 5
1%
#250000
0%
#255000
b110 5
1%
#260000
0%
#265000
b111 5
1%
#270000
0%
#275000
b10 :
b0 5
1%
#280000
0%
#285000
b1 5
1%
#290000
0%
#295000
b10 5
1%
#300000
0%
#305000
b11 5
1%
#310000
0%
#315000
b100 5
1%
#320000
0%
#325000
b101 5
1%
#330000
b0 >
0%
#335000
b110 5
1%
#340000
0%
#345000
b111 5
1%
#350000
0%
#355000
b1000 5
1%
#360000
0%
#365000
b1001 5
1%
#370000
0%
#375000
b1010 5
1%
#380000
0%
#385000
b1011 5
1%
#390000
0%
#395000
b1100 5
1%
#400000
0%
#405000
b1101 5
1%
#410000
0%
#415000
b1110 5
1%
#420000
0%
#425000
b1111 5
1%
#430000
0%
#435000
b1 4
b0 5
1%
#440000
0%
#445000
b1 5
1%
#450000
0%
#455000
b10 5
1%
#460000
0%
#465000
b11 5
1%
#470000
0%
#475000
b100 5
1%
#480000
0%
#485000
b101 5
1%
#490000
b1 >
0%
#495000
b110 5
1%
#500000
0%
#505000
b111 5
1%
#510000
0%
#515000
b1000 5
1%
#520000
0%
#525000
b1001 5
1%
#530000
0%
#535000
b1010 5
1%
#540000
0%
#545000
b1011 5
1%
#550000
0%
#555000
b1100 5
1%
#560000
0%
#565000
b1101 5
1%
#570000
0%
#575000
b1110 5
1%
#580000
0%
#585000
b1111 5
1%
#590000
0%
#595000
b10 4
b0 5
1%
#600000
0%
#605000
b1 5
1%
#610000
0%
#615000
b10 5
1%
#620000
0%
#625000
b11 5
1%
#630000
0%
#635000
b100 5
1%
#640000
0%
#645000
b101 5
1%
#650000
b10 >
0%
#655000
b110 5
1%
#660000
0%
#665000
b111 5
1%
#670000
0%
#675000
b1000 5
1%
#680000
0%
#685000
b1001 5
1%
#690000
0%
#695000
b1010 5
1%
#700000
0%
#705000
b1011 5
1%
#710000
0%
#715000
b1100 5
1%
#720000
0%
#725000
b1101 5
1%
#730000
0%
#735000
b1110 5
1%
#740000
0%
#745000
b1111 5
1%
#750000
0%
#755000
b11 4
b0 5
1%
#760000
0%
#765000
b1 5
1%
#770000
0%
#775000
b10 5
1%
#780000
0%
#785000
b11 5
1%
#790000
0%
#795000
b100 5
1%
#800000
0%
#805000
b101 5
1%
#810000
b11 >
0%
#815000
b110 5
1%
#820000
0%
#825000
b111 5
1%
#830000
0%
#835000
b1000 5
1%
#840000
0%
#845000
b1001 5
1%
#850000
0%
#855000
b1010 5
1%
#860000
0%
#865000
b1011 5
1%
#870000
0%
#875000
b1100 5
1%
#880000
0%
#885000
b1101 5
1%
#890000
0%
#895000
b1110 5
1%
#900000
0%
#905000
b1111 5
1%
#910000
0%
#915000
b100 4
b0 5
1%
#920000
0%
#925000
b1 5
1%
#930000
0%
#935000
b10 5
1%
#940000
0%
#945000
b11 5
1%
#950000
0%
#955000
b100 5
1%
#960000
0%
#965000
b101 5
1%
#970000
b100 >
0%
#975000
b110 5
1%
#980000
0%
#985000
b111 5
1%
#990000
0%
#995000
b1000 5
1%
#1000000
0%
#1005000
b1001 5
1%
#1010000
0%
#1015000
b1010 5
1%
#1020000
0%
#1025000
b1011 5
1%
#1030000
0%
#1035000
b1100 5
1%
#1040000
0%
#1045000
b1101 5
1%
#1050000
0%
#1055000
b1110 5
1%
#1060000
0%
#1065000
b1111 5
1%
#1070000
0%
#1075000
b101 4
b0 5
1%
#1080000
0%
#1085000
b1 5
1%
#1090000
0%
#1095000
b10 5
1%
#1100000
0%
#1105000
b11 5
1%
#1110000
0%
#1115000
b100 5
1%
#1120000
0%
#1125000
b101 5
1%
#1130000
b101 >
0%
#1135000
b110 5
1%
#1140000
0%
#1145000
b111 5
1%
#1150000
0%
#1155000
b1000 5
1%
#1160000
0%
#1165000
b1001 5
1%
#1170000
0%
#1175000
b1010 5
1%
#1180000
0%
#1185000
b1011 5
1%
#1190000
0%
#1195000
b1100 5
1%
#1200000
0%
#1205000
b1101 5
1%
#1210000
0%
#1215000
b1110 5
1%
#1220000
0%
#1225000
b1111 5
1%
#1230000
0%
#1235000
b110 4
b0 5
1%
#1240000
0%
#1245000
b1 5
1%
#1250000
0%
#1255000
b10 5
1%
#1260000
0%
#1265000
b11 5
1%
#1270000
0%
#1275000
b100 5
1%
#1280000
0%
#1285000
b101 5
1%
#1290000
b110 >
0%
#1295000
b110 5
1%
#1300000
0%
#1305000
b111 5
1%
#1310000
0%
#1315000
b1000 5
1%
#1320000
0%
#1325000
b1001 5
1%
#1330000
0%
#1335000
b1010 5
1%
#1340000
0%
#1345000
b1011 5
1%
#1350000
0%
#1355000
b1100 5
1%
#1360000
0%
#1365000
b1101 5
1%
#1370000
0%
#1375000
b1110 5
1%
#1380000
0%
#1385000
b1111 5
1%
#1390000
0%
#1395000
b111 4
b0 5
1%
#1400000
0%
#1405000
b1 5
1%
#1410000
0%
#1415000
b10 5
1%
#1420000
0%
#1425000
b11 5
1%
#1430000
0%
#1435000
b100 5
1%
#1440000
0%
#1445000
b101 5
1%
#1450000
b111 >
0%
#1455000
b110 5
1%
#1460000
0%
#1465000
b111 5
1%
#1470000
0%
#1475000
b1000 5
1%
#1480000
0%
#1485000
b1001 5
1%
#1490000
0%
#1495000
b1010 5
1%
#1500000
0%
#1505000
b1011 5
1%
#1510000
0%
#1515000
b1100 5
1%
#1520000
0%
#1525000
b1101 5
1%
#1530000
0%
#1535000
b1110 5
1%
#1540000
0%
#1545000
b1111 5
1%
#1550000
0%
#1555000
b11 :
b0 5
1%
#1560000
0%
#1565000
b1 5
1%
#1570000
0%
#1575000
b10 5
1%
#1580000
0%
#1585000
b11 5
1%
#1590000
0%
#1595000
b100 5
1%
#1600000
0%
#1605000
b101 5
1%
#1610000
1(
b1000 >
0%
#1615000
b110 5
17
1%
#1620000
0%
#1625000
18
b111 5
1%
#1630000
0%
#1635000
b1000 5
1%
#1640000
0%
#1645000
b1001 5
1%
#1650000
0%
#1655000
b1010 5
1%
#1660000
0%
#1665000
b1011 5
1%
#1670000
0%
#1675000
b1100 5
1%
#1680000
0%
#1685000
b1101 5
1%
#1690000
0%
#1695000
b1110 5
1%
#1700000
0%
#1705000
b1111 5
1%
#1710000
0%
#1715000
b0 :
1"
b0 5
1%
#1720000
0%
#1725000
0"
b0 &
b1 -
1%
